LICENSE
README.md
setup.py
ComPP/__init__.py
ComPP/compp.py
ComPP/config.json
ComPP.egg-info/PKG-INFO
ComPP.egg-info/SOURCES.txt
ComPP.egg-info/dependency_links.txt
ComPP.egg-info/requires.txt
ComPP.egg-info/top_level.txt
bin/compp