Metadata-Version: 2.1
Name: ComPP
Version: 1.0.5
Summary: UNKNOWN
Home-page: https://github.com/sec-it/ComPP
Author: Zeecka
License: MIT License
Project-URL: Source, https://github.com/sec-it/ComPP
Project-URL: Tracker, https://github.com/sec-it/ComPP/issues
Platform: UNKNOWN
Classifier: Development Status :: 5 - Production/Stable
Classifier: Environment :: Console
Classifier: Intended Audience :: Information Technology
Classifier: License :: OSI Approved :: MIT License
Classifier: Natural Language :: English
Classifier: Programming Language :: Python :: 3.7
Classifier: Programming Language :: Python :: 3.8
Classifier: Programming Language :: Python :: 3.9
Classifier: Programming Language :: Python :: 3.10
Classifier: Programming Language :: Python :: Implementation
Classifier: Topic :: Security
Requires-Python: >=3.7
License-File: LICENSE
